upd_subagent/__init__.py
upd_subagent-0.1.1.dist-info/METADATA
upd_subagent-0.1.1.dist-info/WHEEL
upd_subagent-0.1.1.dist-info/RECORD
