Metadata-Version: 2.4
Name: upd-subagent
Version: 0.1.1
Summary: CLI tool for updating Claude Code subagents from git.
Project-URL: Repository, https://upd.dev/skills/agent-skills-project
License-Expression: MIT
Keywords: agent,ai,claude,claude-code,subagent
Requires-Python: >=3.10
